{
  "name": "The Gods Punish and Defend",
  "type": "ability",
  "img": "icons/svg/item-bag.svg",
  "system": {
    "source": {
      "book": "",
      "page": "",
      "license": "",
      "revision": 1
    },
    "_dsid": "censor-ability-7",
    "keywords": [
      "melee",
      "strike",
      "weapon"
    ],
    "type": "action",
    "category": "heroic",
    "resource": 3,
    "trigger": "",
    "distance": {
      "type": "melee",
      "primary": 1,
      "secondary": 0,
      "tertiary": null
    },
    "damageDisplay": "melee",
    "target": {
      "type": "creature",
      "value": "1"
    },
    "power": {
      "roll": {
        "formula": "@chr",
        "characteristics": [
          "might"
        ]
      },
      "effects": {
        "iVf8nQAePeD1OKMN": {
          "type": "damage",
          "_id": "iVf8nQAePeD1OKMN",
          "_key": "iVf8nQAePeD1OKMN",
          "name": "",
          "damage": {
            "tier1": {
              "types": [
                "holy"
              ],
              "value": "5+@chr",
              "potency": {
                "characteristic": null,
                "value": null
              },
              "display": ""
            },
            "tier2": {
              "types": [
                "holy"
              ],
              "value": "8+@chr",
              "potency": {
                "characteristic": null,
                "value": null
              },
              "display": ""
            },
            "tier3": {
              "types": [
                "holy"
              ],
              "value": "11+@chr",
              "potency": {
                "characteristic": null,
                "value": null
              },
              "display": ""
            }
          }
        }
      }
    },
    "effect": {
      "before": "",
      "after": "You can spend a Recovery to allow yourself or one ally within 10 squares of you to regain Stamina equal to your Recovery value."
    },
    "spend": {
      "value": null,
      "text": ""
    },
    "story": "You channel holy energy to smite a foe and heal an ally."
  },
  "effects": [

  ],
  "folder": null,
  "flags": {
  },
  "_stats": {
    "compendiumSource": null,
    "coreVersion": "12.331",
    "systemId": "draw-steel",
    "systemVersion": "0.6.2",
    "createdTime": 1740757635615,
    "modifiedTime": 1740757635615,
    "lastModifiedBy": "z2R22m76IkusoFkR"
  },
  "sort": 0,
  "ownership": {
    "default": 0,
    "F1cSR286wTbtHGDL": 3
  },
  "_key": "!items!censor-ability-7!astring",
  "_id": "censorability7aa"
}